reformer.py
reformer-0.1.3.dist-info/DESCRIPTION.rst
reformer-0.1.3.dist-info/METADATA
reformer-0.1.3.dist-info/RECORD
reformer-0.1.3.dist-info/WHEEL
reformer-0.1.3.dist-info/metadata.json
reformer-0.1.3.dist-info/top_level.txt
